eth_tester/__init__.py
eth_tester/constants.py
eth_tester/exceptions.py
eth_tester/main.py
eth_tester/rpc.py
eth_tester/backends/__init__.py
eth_tester/backends/base.py
eth_tester/backends/common.py
eth_tester/backends/mock/__init__.py
eth_tester/backends/mock/common.py
eth_tester/backends/mock/factory.py
eth_tester/backends/mock/main.py
eth_tester/backends/mock/serializers.py
eth_tester/backends/pyevm/__init__.py
eth_tester/backends/pyevm/main.py
eth_tester/backends/pyevm/serializers.py
eth_tester/backends/pyevm/utils.py
eth_tester/normalization/__init__.py
eth_tester/normalization/base.py
eth_tester/normalization/common.py
eth_tester/normalization/default.py
eth_tester/normalization/inbound.py
eth_tester/normalization/outbound.py
eth_tester/tools/__init__.py
eth_tester/tools/gas_burner_contract.py
eth_tester/utils/__init__.py
eth_tester/utils/accounts.py
eth_tester/utils/address.py
eth_tester/utils/backend_testing.py
eth_tester/utils/emitter_contract.py
eth_tester/utils/encoding.py
eth_tester/utils/filters.py
eth_tester/utils/math_contract.py
eth_tester/utils/module_loading.py
eth_tester/utils/throws_contract.py
eth_tester/utils/transactions.py
eth_tester/validation/__init__.py
eth_tester/validation/base.py
eth_tester/validation/common.py
eth_tester/validation/default.py
eth_tester/validation/inbound.py
eth_tester/validation/outbound.py
eth_tester-0.12.0b2.dist-info/LICENSE
eth_tester-0.12.0b2.dist-info/METADATA
eth_tester-0.12.0b2.dist-info/WHEEL
eth_tester-0.12.0b2.dist-info/top_level.txt
eth_tester-0.12.0b2.dist-info/RECORD
