Metadata-Version: 2.1
Name: eth-tester
Version: 0.12.0b2
Summary: eth-tester: Tools for testing Ethereum applications.
Home-page: https://github.com/ethereum/eth-tester
Author: The Ethereum Foundation
Author-email: snakecharmers@ethereum.org
License: MIT
Keywords: ethereum
Classifier: Development Status :: 2 - Pre-Alpha
Classifier: Intended Audience :: Developers
Classifier: License :: OSI Approved :: MIT License
Classifier: Natural Language :: English
Classifier: Programming Language :: Python :: 3
Classifier: Programming Language :: Python :: 3.8
Classifier: Programming Language :: Python :: 3.9
Classifier: Programming Language :: Python :: 3.10
Classifier: Programming Language :: Python :: 3.11
Classifier: Programming Language :: Python :: 3.12
Requires-Python: >=3.8,<4
License-File: LICENSE
Requires-Dist: eth-abi>=3.0.1
Requires-Dist: eth-account>=0.12.3
Requires-Dist: eth-keys>=0.4.0
Requires-Dist: eth-utils>=2.0.0
Requires-Dist: rlp>=3.0.0
Requires-Dist: semantic_version>=2.6.0
Provides-Extra: dev
Requires-Dist: build>=0.9.0; extra == "dev"
Requires-Dist: bumpversion>=0.5.3; extra == "dev"
Requires-Dist: ipython; extra == "dev"
Requires-Dist: pre-commit>=3.4.0; extra == "dev"
Requires-Dist: tox>=4.0.0; extra == "dev"
Requires-Dist: twine; extra == "dev"
Requires-Dist: wheel; extra == "dev"
Requires-Dist: towncrier<22,>=21; extra == "dev"
Requires-Dist: pytest>=7.0.0; extra == "dev"
Requires-Dist: pytest-xdist<3,>=2.0.0; extra == "dev"
Requires-Dist: eth-hash[pycryptodome]<1.0.0,>=0.1.4; extra == "dev"
Requires-Dist: py-evm<0.11.0b0,>=0.10.0b0; extra == "dev"
Requires-Dist: eth-hash[pysha3]<1.0.0,>=0.1.4; implementation_name == "cpython" and extra == "dev"
Requires-Dist: eth-hash[pycryptodome]<1.0.0,>=0.1.4; implementation_name == "pypy" and extra == "dev"
Provides-Extra: docs
Requires-Dist: towncrier<22,>=21; extra == "docs"
Provides-Extra: test
Requires-Dist: pytest>=7.0.0; extra == "test"
Requires-Dist: pytest-xdist<3,>=2.0.0; extra == "test"
Requires-Dist: eth-hash[pycryptodome]<1.0.0,>=0.1.4; extra == "test"
Provides-Extra: py-evm
Requires-Dist: py-evm<0.11.0b0,>=0.10.0b0; extra == "py-evm"
Requires-Dist: eth-hash[pysha3]<1.0.0,>=0.1.4; implementation_name == "cpython" and extra == "py-evm"
Requires-Dist: eth-hash[pycryptodome]<1.0.0,>=0.1.4; implementation_name == "pypy" and extra == "py-evm"
Provides-Extra: pyevm
Requires-Dist: py-evm<0.11.0b0,>=0.10.0b0; extra == "pyevm"
Requires-Dist: eth-hash[pysha3]<1.0.0,>=0.1.4; implementation_name == "cpython" and extra == "pyevm"
Requires-Dist: eth-hash[pycryptodome]<1.0.0,>=0.1.4; implementation_name == "pypy" and extra == "pyevm"
